{
  "approx_single_thread_qps": 968.9363839972406,
  "avg_batch_read_total_ms": 0.7873997495,
  "avg_candidates_per_unique_payload_page": -1.0,
  "avg_duplicate_page_like_ratio": -1.0,
  "avg_duplicate_vector_count": 751.4956,
  "avg_ex_latency_ms": 0.8055251,
  "avg_io_wait_ms": 0.0,
  "avg_pages_read": 177.5684,
  "avg_payload_candidates": 0.0,
  "avg_payload_physical_bytes": 0.0,
  "avg_payload_read_wait_ms": 0.0,
  "avg_postings_touched": 95.4665,
  "avg_recall": 0.98868,
  "avg_requested_read_bytes": 727320.1664,
  "avg_total_latency_ms": 1.0320595,
  "avg_unique_payload_pages": 0.0,
  "gini_pages_per_query": 0.07994089421315964,
  "gini_payload_bytes_per_query": -1.0,
  "gini_payload_wait_per_query": -1.0,
  "input_query_csv": "/home/ray/code/SPTAG/results/io_analysis/sift1m_official_u8default_20260430/sweeps_20260430_strict_v2/st2_nt40_ir96_pl8/query_io_stats.csv",
  "io_wait_over_ex": 0.0,
  "p50_total_latency_ms": 1.051,
  "p95_ex_latency_ms": 0.985,
  "p95_payload_read_wait_ms": -1.0,
  "p95_total_latency_ms": 1.218,
  "p99_total_latency_ms": 1.282,
  "payload_read_wait_over_ex": -1.0,
  "payload_stats_supported": false,
  "payload_wait_supported": false,
  "query_count": 10000,
  "recommendation": {
    "ranking": [
      {
        "direction": "M4",
        "score": 1
      },
      {
        "direction": "M1",
        "score": 0
      },
      {
        "direction": "M2-H",
        "score": 0
      }
    ],
    "reasons": [
      "payload-locality columns are unavailable/zero in this run; provide payload trace or richer instrumentation",
      "payload read wait columns are unavailable/zero; M1 scoring is conservative"
    ],
    "top_direction": "M4"
  },
  "top10_query_share_pages": 0.12030800525318694,
  "top10_query_share_payload_bytes": 0.0,
  "top10_query_share_payload_wait": -1.0,
  "top1_query_share_payload_wait": -1.0
}